kernelparcial/__init__.py
kernelparcial/modulo.py
kernelparcial-0.1.0.dist-info/METADATA
kernelparcial-0.1.0.dist-info/WHEEL
kernelparcial-0.1.0.dist-info/top_level.txt
kernelparcial-0.1.0.dist-info/RECORD
