Metadata-Version: 2.1
Name: kernelparcial
Version: 0.1.0
Summary: library ML
Author: M Luciano
Author-email: luciano.munoz1@udea.edu.co
License: MIT
Requires-Python: >=3.10.12
Requires-Dist: numpy
Requires-Dist: matplotlib
Requires-Dist: pandas
